AUTHORS.rst
CONTRIBUTING.rst
HISTORY.rst
LICENSE
MANIFEST.in
README.rst
fwffr.py
setup.cfg
setup.py
docs/Makefile
docs/authors.rst
docs/conf.py
docs/contributing.rst
docs/history.rst
docs/index.rst
docs/installation.rst
docs/make.bat
docs/readme.rst
docs/usage.rst
fwffr.egg-info/PKG-INFO
fwffr.egg-info/SOURCES.txt
fwffr.egg-info/dependency_links.txt
fwffr.egg-info/not-zip-safe
fwffr.egg-info/top_level.txt
tests/__init__.py
tests/test_fwffr.py