Metadata-Version: 1.1
Name: fwffr
Version: 0.4.0
Summary: Fixed-width field format reader
Home-page: https://github.com/GoodRx/fwffr
Author: Kyle Stark
Author-email: kyle@goodrx.com
License: MIT license
Keywords: fwffr
Platform: UNKNOWN
Classifier: Development Status :: 2 - Pre-Alpha
Classifier: Intended Audience :: Developers
Classifier: License :: OSI Approved :: MIT License
Classifier: Natural Language :: English
Classifier: Programming Language :: Python :: 2
Classifier: Programming Language :: Python :: 2.6
Classifier: Programming Language :: Python :: 2.7
Classifier: Programming Language :: Python :: 3
Classifier: Programming Language :: Python :: 3.3
Classifier: Programming Language :: Python :: 3.4
Classifier: Programming Language :: Python :: 3.5
